bento2seldon/__init__.py
bento2seldon/adapter.py
bento2seldon/bento.py
bento2seldon/cache.py
bento2seldon/logging.py
bento2seldon/model.py
bento2seldon/monitoring.py
bento2seldon/py.typed
bento2seldon/seldon.py
bento2seldon/utils.py
bento2seldon-0.4.0.dist-info/LICENSE
bento2seldon-0.4.0.dist-info/WHEEL
bento2seldon-0.4.0.dist-info/METADATA
bento2seldon-0.4.0.dist-info/RECORD
