Metadata-Version: 2.1
Name: bento2seldon
Version: 0.4.0
Summary: This project aims to combine the awesome capabilities of BentoML in packaging models with the powerful Seldon Core engine to deploy such models. It also features an optional cache using Redis that can also be used to make the feedback loop easier by using the request ID to get back the original request and response. For now, it was created for internal use and is in alpha state. But it will soon be prepared to be used by everyone.
Home-page: https://github.com/fernandocamargoai/bento2seldon
License: Apache Software License 2.0
Keywords: machine learning,deployment
Author: fernandocamargoai
Author-email: fernando.camargo.ai@gmail.com
Requires-Python: >=3.7,<4.0
Classifier: Development Status :: 3 - Alpha
Classifier: Intended Audience :: Developers
Classifier: License :: Other/Proprietary License
Classifier: Operating System :: OS Independent
Classifier: Programming Language :: Python :: 3
Classifier: Programming Language :: Python :: 3.10
Classifier: Programming Language :: Python :: 3.7
Classifier: Programming Language :: Python :: 3.8
Classifier: Programming Language :: Python :: 3.9
Classifier: Topic :: Scientific/Engineering :: Artificial Intelligence
Classifier: Topic :: Software Development :: Libraries :: Python Modules
Requires-Dist: BentoML (>=0.12,<0.13)
Requires-Dist: decorator (>=5.0,<6.0)
Requires-Dist: importlib_metadata (>=4.5.0,<5.0.0); python_version < "3.8"
Requires-Dist: pydantic (>=1.8,<2.0)
Requires-Dist: redis (>=3.0,<4.0)
Project-URL: Repository, https://github.com/fernandocamargoai/bento2seldon
